vazha/__init__.py
vazha/command_line.py
vazha/my.py
vazha/test.py
vazha/vazha_to_eng.py
vazha-0.3.dist-info/METADATA
vazha-0.3.dist-info/WHEEL
vazha-0.3.dist-info/entry_points.txt
vazha-0.3.dist-info/top_level.txt
vazha-0.3.dist-info/RECORD
