Metadata-Version: 2.1
Name: vazha
Version: 0.3
Summary: മലയാള പൈത്തൺ
Home-page: UNKNOWN
Author: user9747
Author-email: padinju@gmail.com
License: MIT
Platform: UNKNOWN
